<Quests Title="A Void Dance" Difficulty="Experienced">
    <Member>true</Member>
    <Requirements Name="Quiet Before the Swarm" Type="Quest" Enabled="false">
      <Amount>1</Amount>
    </Requirements>
    <Requirements Name="Druidic Ritual" Type="Quest" Enabled="false">
      <Amount>1</Amount>
    </Requirements>
    <Requirements Name="Hunter" Type="Level" Enabled="false">
      <Amount>46</Amount>
    </Requirements>
    <Requirements Name="Construction" Type="Level" Enabled="false">
      <Amount>47</Amount>
    </Requirements>
    <Requirements Name="Mining" Type="Level" Enabled="false">
      <Amount>47</Amount>
    </Requirements>
    <Requirements Name="Summoning" Type="Level" Enabled="false">
      <Amount>48</Amount>
    </Requirements>
    <Requirements Name="Herblore" Type="Level" Enabled="false">
      <Amount>49</Amount>
    </Requirements>
    <Requirements Name="Woodcutting" Type="Level" Enabled="false">
      <Amount>52</Amount>
    </Requirements>
    <Requirements Name="Thieving" Type="Level" Enabled="false">
      <Amount>54</Amount>
    </Requirements>
    <Requirements Name="Commorb" Type="Item" Enabled="false">
      <Amount>1</Amount>
    </Requirements>
    <Requirements Name="Onion" Type="Item" Enabled="false">
      <Amount>28</Amount>
    </Requirements>
    <Requirements Name="GP" Type="Item" Enabled="false">
      <Amount>30940298</Amount>
    </Requirements>
    <Requirements Name="Black Knight guardian (Lv. 77)" Type="Combat" Enabled="false">
      <Amount>1</Amount>
    </Requirements>
    <Requirements Name="Black Knight guardian (Lv. 110)" Type="Combat" Enabled="false">
      <Amount>1</Amount>
    </Requirements>
    <Rewards Name="Quest Points" Type="QP" Enabled="false">
      <Amount>1</Amount>
    </Rewards>
    <Rewards Name="Void knight commendation" Type="Item" Enabled="false">
      <Amount>1</Amount>
    </Rewards>
    <Rewards Name="Hunter" Type="XP" Enabled="false">
      <Amount>10000</Amount>
    </Rewards>
    <Rewards Name="Herblore" Type="XP" Enabled="false">
      <Amount>10000</Amount>
    </Rewards>
    <Rewards Name="Summoning" Type="XP" Enabled="false">
      <Amount>8000</Amount>
    </Rewards>
    <Rewards Name="Woodcutting" Type="XP" Enabled="false">
      <Amount>8000</Amount>
    </Rewards>
    <Rewards Name="Thieving" Type="XP" Enabled="false">
      <Amount>5000</Amount>
    </Rewards>
    <Rewards Name="Construction" Type="XP" Enabled="false">
      <Amount>5000</Amount>
    </Rewards>
    <Rewards Name="Mining" Type="XP" Enabled="false">
      <Amount>5000</Amount>
    </Rewards>
    <Rewards Name="Treasure Hunter Key" Type="Item" Enabled="false">
      <Amount>2</Amount>
    </Rewards>
    <Completed>false</Completed>
  </Quests>
  